MANIFEST.in
README.md
setup.py
concurrent_videocapture/__init__.py
concurrent_videocapture/concurrent_videocapture.py
concurrent_videocapture.egg-info/PKG-INFO
concurrent_videocapture.egg-info/SOURCES.txt
concurrent_videocapture.egg-info/dependency_links.txt
concurrent_videocapture.egg-info/requires.txt
concurrent_videocapture.egg-info/top_level.txt