Metadata-Version: 2.1
Name: concurrent-videocapture
Version: 0.0.2
Summary: Read opencv cameras concurrently
Home-page: https://github.com/charlielito/concurrent-videocapture
Author: Carlos Alvarez
Author-email: candres.alv@gmail.com
License: GNU
Keywords: opencv,concurrent video
Platform: UNKNOWN
Classifier: Development Status :: 3 - Alpha
Classifier: License :: OSI Approved :: GNU General Public License (GPL)
Classifier: Operating System :: OS Independent
Classifier: Programming Language :: Python
